opposite_day/__init__.py
opposite_day-1.0.0.dist-info/LICENSE
opposite_day-1.0.0.dist-info/METADATA
opposite_day-1.0.0.dist-info/WHEEL
opposite_day-1.0.0.dist-info/top_level.txt
opposite_day-1.0.0.dist-info/RECORD
