Metadata-Version: 2.1
Name: opposite-day
Version: 1.0.0
Summary: It is Opposite Day Now
Home-page: https://github.com/yuvipanda/opposite-day
Author: Yuvi Panda
Author-email: yuvipanda@gmail.com
License: 3 Clause BSD
License-File: LICENSE
